video_writer/__init__.py
video_writer/video_writer.py
videowriter-0.0.dist-info/METADATA
videowriter-0.0.dist-info/WHEEL
videowriter-0.0.dist-info/top_level.txt
videowriter-0.0.dist-info/RECORD
