Metadata-Version: 2.1
Name: videowriter
Version: 0.0
Requires-Dist: opencv-python
